refidxdb/__init__.py
refidxdb/app.py
refidxdb/cli.py
refidxdb/handler.py
refidxdb/refidxdb.py
refidxdb/file/__init__.py
refidxdb/file/csv.py
refidxdb/file/dat.py
refidxdb/url/__init__.py
refidxdb/url/aria.py
refidxdb/url/refidx.py
refidxdb-0.4.0.dist-info/METADATA
refidxdb-0.4.0.dist-info/WHEEL
refidxdb-0.4.0.dist-info/entry_points.txt
refidxdb-0.4.0.dist-info/licenses/LICENSE
refidxdb-0.4.0.dist-info/RECORD
