Metadata-Version: 2.4
Name: refidxdb
Version: 0.4.0
Summary: Python interface for various refractive index databases
Author-email: Mirza Arnaut <mirza.arnaut45@gmail.com>
License: MIT License
License-File: LICENSE
Requires-Python: <4.0,>=3.10
Requires-Dist: click>=8.1.7
Requires-Dist: numpy<2.0.0,>=1.26.4
Requires-Dist: plotext>=5.2.8
Requires-Dist: plotly>=5.24.1
Requires-Dist: polars>=1.12.0
Requires-Dist: pydantic>=2.9.2
Requires-Dist: pyyaml>=6.0.2
Requires-Dist: rich>=13.8.1
Requires-Dist: streamlit>=1.40.1
Requires-Dist: tqdm>=4.66.5
